<annotation>
	<folder>800x600</folder>
	<filename>220.jpg</filename>
	<path>D:\Robot Pengirim Barang S3\10okt21 vehicles\800x600\220.jpg</path>
	<source>
		<database>Unknown</database>
	</source>
	<size>
		<width>800</width>
		<height>600</height>
		<depth>3</depth>
	</size>
	<segmented>0</segmented>
	<object>
		<name>bike</name>
		<pose>Unspecified</pose>
		<truncated>0</truncated>
		<difficult>0</difficult>
		<bndbox>
			<xmin>299</xmin>
			<ymin>299</ymin>
			<xmax>332</xmax>
			<ymax>341</ymax>
		</bndbox>
	</object>
	<object>
		<name>car</name>
		<pose>Unspecified</pose>
		<truncated>1</truncated>
		<difficult>0</difficult>
		<bndbox>
			<xmin>605</xmin>
			<ymin>171</ymin>
			<xmax>800</xmax>
			<ymax>598</ymax>
		</bndbox>
	</object>
	<object>
		<name>car</name>
		<pose>Unspecified</pose>
		<truncated>0</truncated>
		<difficult>0</difficult>
		<bndbox>
			<xmin>235</xmin>
			<ymin>260</ymin>
			<xmax>368</xmax>
			<ymax>326</ymax>
		</bndbox>
	</object>
</annotation>
